README
ez_setup.py
opaf.py
setup.py
OPAF.egg-info/PKG-INFO
OPAF.egg-info/SOURCES.txt
OPAF.egg-info/dependency_links.txt
OPAF.egg-info/requires.txt
OPAF.egg-info/top_level.txt
examples/expansion-0.png
examples/expansion-1.png
examples/expansion-2.png
examples/mini.pdf
examples/mini.xml
examples/textg.pdf
examples/textg.xml
opaflib/__init__.py
opaflib/filters.py
opaflib/lexer.py
opaflib/lzw.py
opaflib/miniPDF.py
opaflib/parser.py
opaflib/xmlast.py
opaflib/xref.py
tests/filters_tst.py