Metadata-Version: 1.0
Name: OPAF
Version: 0.9.2
Summary: Open PDF Analysis Framework
Home-page: http://code.google.com/p/opaf/
Author: Felipe Andres Manzano
Author-email: felipe.andres.manzano@gmail.com
License: New BSD License
Platform: UNKNOWN
Classifier: Development Status :: 4 - Beta
Classifier: Environment :: Console
Classifier: Intended Audience :: Developers
Classifier: License :: OSI Approved :: BSD License
Classifier: Operating System :: POSIX
Classifier: Operating System :: MacOS :: MacOS X
Classifier: Operating System :: Microsoft :: Windows
Classifier: Programming Language :: Python
Classifier: Topic :: Software Development :: Libraries :: Python Modules
Classifier: Natural Language :: English
